Workbook

Sheet Call
A1: Nutanix role-play: call sheet
A2: HOW TO USE: ask the question in column C and type her answer, as KEYWORDS (2-3 words, not sentences) in the yellow cell in column D. Blue = typed by you. Grey = automatic. The Pitch tab and the Brief tab fill themselves from what you type here.
A3: Numbers with no symbols (600000). Dates in her words (mid-April). Don't type sentences: the summary lines write them for you. Targeted questions and the three step-6 needs need a pain type picked in column E (dropdown).
A5: Step | B5: Min | C5: Question (say this) | D5: HER answer (type here) | E5: Pain type (dropdown) | F5: Feeds
A6: 1 AGENDA | B6: 0-2 | C6: "Objective: understand your virtual estate (15-20 min). Last 10 min: decide a next step or part ways. Does that feel fair?"
A7: 2 SITUATION | B7: 2-4 | C7: "Walk me through your estate: what runs on it, how many hosts and VMs, how much storage, how big is the team?" KEYWORDS: 12 hosts, 400 VMs, 150TB, team 5 | F7: Costing
A8: 2 PAIN | B8: 4-8 | C8: HER PAIN: "What did the reseller say that made you agree to the meeting?" KEYWORDS: e.g. renewal price jump | F8: Her pain
C9: WHAT IT AFFECTS: "You mentioned [her words]. What does that affect over the next 6 to 12 months?" KEYWORDS: e.g. storage arrays, network upgrade | F9: What it affects
C10: WHY THAT'S A PROBLEM: "What's driving [her word] to be a priority?" (two things? "Which matters most?") KEYWORDS: e.g. end of support, patient data | F10: Why it's a problem
C11: FOCUS CHECK: "Is this the thing to focus on, or will something overpower it?" (once, no cell)
A12: 3 NUMBER | B12: 8-12 | C12: "You said [her words]. Roughly how much has it gone up by? 10%, 50%, or more?" Then: "Can you put a monetary value on it?" Fill the 3 numbers:
C13: -> Pays now (per year) | F13: Numbers
C14: -> Quote she has seen (per year) | F14: Numbers
C15: -> What she can absorb without cutting anything (per year) | F15: Numbers
C16: -> Increase % (automatic) | D16: =IF(AND(ISNUMBER($D$13),ISNUMBER($D$14)),IF($D$13>0,$D$14/$D$13-1,""),"") | F16: Numbers
C17: -> Gap per year: quote minus what she can absorb (automatic) | D17: =IF(AND(ISNUMBER($D$14),ISNUMBER($D$15)),$D$14-$D$15,"") | F17: Numbers
C18: "When is the deadline for this?" KEYWORDS: board date | F18: Timeframe
C19: -> Renewal date KEYWORDS: e.g. end of June | F19: Timeframe
C20: "What happens if nothing changes by then?" KEYWORDS: sign at new price, project slips | F20: Doing nothing
C21: SUMMARY (automatic): read it straight off the sheet, then "Did I get that right?" | D21: =IF(COUNT($D$14,$D$13,$D$15)<3,"(fill in the three numbers above)","So the quote is "&TEXT($D$14,"#,##0")&" against "&TEXT($D$13,"#,##0")&" now. You can absorb "&TEXT($D$15,"#,##0")&". The board is "&$D$18&", the renewal is "&$D$19&". Did I get that right?") -> (fill in the three numbers above) | F21: Summary
A22: 4 CAUSE | B22: 12-16 | C22: "Why do you think this is going to hit you so hard?" then "To what extent is [her cause] an issue for YOU?" KEYWORDS: her cause | F22: Cause
C23: =IF($E23="","TARGETED root-cause question: pick a pain type in column E, the question appears here",IFERROR(INDEX(Lookup!$H$6:$H$25,MATCH($E23,Lookup!$A$6:$A$25,0)),"(pain type not in Lookup)")) -> TARGETED root-cause question: pick a pain type in column E, the question appears here | F23: Cause
C24: "What else is driving this to matter right now?" Ask once, no recap. KEYWORDS: her answers (your Y's) | F24: Y's for the pitch
C25: SUMMARY (automatic): cause + timing in her words, then "Did I get that right?" | D25: =IF(OR($D$22="",$D$24=""),"(fill in her cause and what else is driving it)","So it hits hard because "&$D$22&", and right now it matters because "&$D$24&". Did I get that right?") -> (fill in her cause and what else is driving it) | F25: Summary
A26: 5 IMPACT | B26: 16-21 | C26: "What ripple effect is this having on other people? Who else feels this, and why is it a concern to them?" KEYWORDS: who + why | F26: Buying box
C27: =IF($E27="","TARGETED impact question: pick a pain type in column E, the question appears here",IFERROR(INDEX(Lookup!$I$6:$I$25,MATCH($E27,Lookup!$A$6:$A$25,0)),"(pain type not in Lookup)")) -> TARGETED impact question: pick a pain type in column E, the question appears here | F27: Impact
C28: "How does this affect you personally?" KEYWORDS: her personal stake | F28: Y's for the pitch
C29: "Who else needs to sign off on this?" then "What would they need to see?" KEYWORDS: names | F29: Buying box
C30: "Where would the money for this come from? Is it set aside, or does it need requesting?" KEYWORDS: budget pot, owner | F30: Buying box
A31: 6 OUTCOME | B31: 21-23 | C31: "What do you need to happen before [her date]?" Use HER date and HER word. One need per row, then pick a pain type in column E.
C32: -> Need 1 | F32: Pitch
C33: -> Need 2 | F33: Pitch
C34: -> Need 3 | F34: Pitch
C35: "Which of those matters most to you?" Pick 1, 2 or 3. | F35: Pitch order
C36: "Why does that matter to you personally?" KEYWORDS: her reason | F36: Y's for the pitch
C37: SUMMARY of her needs only (automatic): say it, then "Did I get that right?" | D37: =IF(OR(COUNTA($D$32:$D$34)<3,NOT(AND($D$35>=1,$D$35<=3))),"(type all three needs and pick which matters most)","So you need: "&$D$32&"; "&$D$33&"; and "&$D$34&". The most important is: "&INDEX($D$32:$D$34,IF(AND($D$35>=1,$D$35<=3),$D$35,1))&". Did I get that right?") -> (type all three needs and pick which matters most) | F37: Summary
A38: 9 CLOSE | B38: 27-30 | C38: "We said we'd decide if a next step makes sense. Does it? What do you need from us beforehand? Who else should be in the room?" KEYWORDS: who | F38: Next step
C39: -> Date and time agreed for the working session | F39: Next step
C40: SCRATCH: anything else she says (no cell feeds from this) | F40: Notes

Sheet Pitch
A1: Pitch builder (fills itself from the Call tab)
A2: Nothing to type here. After step 6 say "Can I try a few ideas on you?" and read down column F: opener, then three lines. Formula: We do X. You told me Y. So here's how that fits. Her top need goes first.
A3: ="Needs typed: "&COUNTA(Call!$D$32:$D$34)&" of 3. Pain types picked: "&COUNTA(Call!$E$32:$E$34)&" of 3. Top need chosen: "&IF(AND(Call!$D$35>=1,Call!$D$35<=3),"yes","no (using need 1)") -> Needs typed: 0 of 3. Pain types picked: 0 of 3. Top need chosen: no (using need 1)
A4: # | B4: Need # (her order) | C4: Her words (Y) | D4: Pain type | E4: We do (X) | F4: SAY THIS | G4: If she asks 'how?' (fact + source)
A5: 1 | C5: Ask permission | F5: "Can I try a few ideas on you?"
A6: 2 | C6: Opener (one sentence) | F6: "A lot of VMware customers are looking at alternatives since Broadcom changed the licensing. Nutanix puts your servers, storage and networking into one system, so you manage it from one place."
A7: 3 | B7: =IF(AND(Call!$D$35>=1,Call!$D$35<=3),Call!$D$35,1) -> 1 | C7: =IF(INDEX(Call!$D$32:$D$34,B7)="","",INDEX(Call!$D$32:$D$34,B7)) | D7: =IF(INDEX(Call!$E$32:$E$34,B7)="","",INDEX(Call!$E$32:$E$34,B7)) | E7: =IF(D7="","",IFERROR(INDEX(Lookup!$C$6:$C$25,MATCH(D7,Lookup!$A$6:$A$25,0)),"(pain type not in Lookup)")) | F7: =IF(C7="","(type need "&B7&" on the Call tab)",IF(D7="","We [pick a pain type for need "&B7&" on the Call tab]. You told me "&C7&" matters most"&". So here's how that fits.","We "&E7&". You told me "&C7&" matters most"&". So here's how that fits.")) -> (type need 1 on the Call tab) | G7: =IF(D7="","",IFERROR(INDEX(Lookup!$D$6:$D$25,MATCH(D7,Lookup!$A$6:$A$25,0))&" Source: "&INDEX(Lookup!$F$6:$F$25,MATCH(D7,Lookup!$A$6:$A$25,0)),"(no fact on file)"))
A8: 4 | B8: =IF(B7=1,2,1) -> 2 | C8: =IF(INDEX(Call!$D$32:$D$34,B8)="","",INDEX(Call!$D$32:$D$34,B8)) | D8: =IF(INDEX(Call!$E$32:$E$34,B8)="","",INDEX(Call!$E$32:$E$34,B8)) | E8: =IF(D8="","",IFERROR(INDEX(Lookup!$C$6:$C$25,MATCH(D8,Lookup!$A$6:$A$25,0)),"(pain type not in Lookup)")) | F8: =IF(C8="","(type need "&B8&" on the Call tab)",IF(D8="","We [pick a pain type for need "&B8&" on the Call tab]. You told me "&C8&" matters"&". So here's how that fits.","We "&E8&". You told me "&C8&" matters"&". So here's how that fits.")) -> (type need 2 on the Call tab) | G8: =IF(D8="","",IFERROR(INDEX(Lookup!$D$6:$D$25,MATCH(D8,Lookup!$A$6:$A$25,0))&" Source: "&INDEX(Lookup!$F$6:$F$25,MATCH(D8,Lookup!$A$6:$A$25,0)),"(no fact on file)"))
A9: 5 | B9: =IF(B7=3,2,3) -> 3 | C9: =IF(INDEX(Call!$D$32:$D$34,B9)="","",INDEX(Call!$D$32:$D$34,B9)) | D9: =IF(INDEX(Call!$E$32:$E$34,B9)="","",INDEX(Call!$E$32:$E$34,B9)) | E9: =IF(D9="","",IFERROR(INDEX(Lookup!$C$6:$C$25,MATCH(D9,Lookup!$A$6:$A$25,0)),"(pain type not in Lookup)")) | F9: =IF(C9="","(type need "&B9&" on the Call tab)",IF(D9="","We [pick a pain type for need "&B9&" on the Call tab]. You told me "&C9&" matters"&". So here's how that fits.","We "&E9&". You told me "&C9&" matters"&". So here's how that fits.")) -> (type need 3 on the Call tab) | G9: =IF(D9="","",IFERROR(INDEX(Lookup!$D$6:$D$25,MATCH(D9,Lookup!$A$6:$A$25,0))&" Source: "&INDEX(Lookup!$F$6:$F$25,MATCH(D9,Lookup!$A$6:$A$25,0)),"(no fact on file)"))
A10: 6 | C10: Check it | F10: "How does that sit against what you need?" Then stop talking. If she asks "what would the first step be?", go straight to the close below.
A12: CLOSE (step 9, 27-30 min): read this after the objections
A13: 1 | C13: Decision | F13: "We said we'd decide if a next step makes sense. Does it?"
A14: 2 | C14: Before the session | F14: "What do you need from us beforehand?"
A15: 3 | C15: Book it (automatic) | F15: =IF(Call!$D$18="","""Let's book a working session, worked back from your deadline. Who else should be in the room?""","""Let's book a working session before "&Call!$D$18&", worked back from that date. In the room: you, "&IF(Call!$D$29="","your finance and compliance leads",Call!$D$29)&", the reseller and our engineer. Who else should be in the room?""") -> "Let's book a working session, worked back from your deadline. Who else should be in the room?"
A16: 4 | C16: Lock it in | F16: "I'll send dates and a one-page recap today."
A18: Her numbers and notes (automatic)
A19: Pays now | C19: =IF(Call!$D$13="","",Call!$D$13)
A20: Quote | C20: =IF(Call!$D$14="","",Call!$D$14)
A21: Increase | C21: =Call!$D$16
A22: She can absorb | C22: =IF(Call!$D$15="","",Call!$D$15)
A23: Gap per year | C23: =Call!$D$17
A24: Board / decision date | C24: =IF(Call!$D$18="","",Call!$D$18)
A25: Renewal date | C25: =IF(Call!$D$19="","",Call!$D$19)
A26: Estate (hosts, VMs, storage) | C26: =IF(Call!$D$7="","",Call!$D$7)
A27: Her top need | C27: =IF(COUNTA(Call!$D$32:$D$34)=0,"",IF(INDEX(Call!$D$32:$D$34,IF(AND(Call!$D$35>=1,Call!$D$35<=3),Call!$D$35,1))="","",INDEX(Call!$D$32:$D$34,IF(AND(Call!$D$35>=1,Call!$D$35<=3),Call!$D$35,1))))
A28: Personal stake | C28: =IF(Call!$D$36="","",Call!$D$36)
A29: Signs off | C29: =IF(Call!$D$29="","",Call!$D$29)
A31: Slips to avoid: ARR means annual recurring revenue, not 'average'. Never 'zero downtime'. Never 'cheaper, safer, faster' without proof. Never put words in her mouth. Never run down VMware.

Sheet Brief
A1: Interview brief: did you do everything they ask?
A2: From the Nutanix assessment briefing: 4 things you must do in the 30 minutes, 7 things they score you on (1-5 each, 35 total), and 3 guidelines. 'Auto' ticks itself from the Call tab. 'Your check' is for you after the run.
A4: A. What they ask you to do
A5: # | B5: They ask for | C5: Where the sheet covers it | D5: Auto check | E5: Your check | F5: Notes after the run
A6: 1a | B6: Uncover the customer's current situation | C6: Step 2 situation: hosts, VMs, storage, team | D6: =IF(COUNTA(Call!$D$7)>=1,"Done","Not yet") -> Not yet
A7: 1b | B7: Uncover pain points / challenges | C7: Steps 2 and 4: pain, what it affects, why it is a problem, cause | D7: =IF(COUNTA(Call!$D$8,Call!$D$9,Call!$D$10,Call!$D$22)>=3,"Done","Not yet") -> Not yet
A8: 1c | B8: Uncover needs | C8: Step 6: three needs and which matters most | D8: =IF(AND(COUNTA(Call!$D$32:$D$34)=3,AND(Call!$D$35>=1,Call!$D$35<=3)),"Done","Not yet") -> Not yet
A9: 1d | B9: Uncover implications of doing nothing | C9: Step 3: 'what if nothing changes', step 5 impact | D9: =IF(COUNTA(Call!$D$20,Call!$D$26,Call!$D$28)>=2,"Done","Not yet") -> Not yet
A10: 1e | B10: Uncover the timeframe | C10: Step 3: board and renewal dates | D10: =IF(COUNTA(Call!$D$18,Call!$D$19)>=2,"Done","Not yet") -> Not yet
A11: 2 | B11: Introduce Nutanix: high-level business outcomes, keep her attention | C11: Pitch tab lines 2 to 5 (outcomes are HER needs) | D11: (manual)
A12: 3 | B12: Overcome objections elegantly | C12: Objections tab. Mark yourself after the run. | D12: (manual)
A13: 4 | B13: Agree a specific next step | C13: Step 9 and the Close block on the Pitch tab | D13: =IF(COUNTA(Call!$D$39,Call!$D$38)>=2,"Done","Not yet") -> Not yet
A15: B. What they score you on (the assessment grid)
A16: # | B16: Criterion | C16: What to do | E16: Your score 1-5 | F16: Why / what to fix
A17: 1 | B17: Understanding of the customer | C17: Her words, her numbers, her dates, her personal stake. Never put words in her mouth.
A18: 2 | B18: Level of preparation | C18: Estate questions ready, targeted questions picked from Lookup, close planned, Nutanix terms known (Basics tab).
A19: 3 | B19: Presentation skills and communication | C19: Say the pitch, don't read it. Plain English. No filler 'okay'.
A20: 4 | B20: Understanding of Nutanix at base level | C20: Say the Basics tab answers in your own words, with no jargon.
A21: 5 | B21: Ability to deal with objections | C21: Agree, don't over-promise, ask what she needs. Every objection answered.
A22: 6 | B22: Control over the meeting and time management | C22: Agenda in the first 2 minutes. Pitch by 23:00, close by 27:00.
A23: 7 | B23: Clear next action | C23: Date, people, purpose, recap sent today.
B24: Total | E24: =IF(COUNT(E17:E23)=0,"",SUM(E17:E23)&" / 35")
A26: C. Time check (type the minute you reached each point)
B27: Point | C27: Target | D27: Minute reached | F27: Status
B28: Pitch started (after step 6) | C28: by 23:00 | F28: =IF(D28="","",IF(D28<=23,"On time","Late by "&(D28-23)&" min"))
B29: Close started (after objections) | C29: by 27:00 | F29: =IF(D29="","",IF(D29<=27,"On time","Late by "&(D29-27)&" min"))
B30: Call ended | C30: by 30:00 | F30: =IF(D30="","",IF(D30<=30,"On time","Late by "&(D30-30)&" min"))
A32: D. Their three guidelines
B33: Qualify before presenting. Understanding the prospect is key, so spend some time on discovery first.
B34: Keep the Nutanix introduction simple and outcome-focused, not technical.
B35: Prepare for a Q&A afterwards (Basics and Objections tabs).

Sheet Basics
A1: Nutanix basics: say these plainly if she asks
A2: They test 'understanding of Nutanix at base level'. Say each answer in your own words, short. If you don't know something: "I don't know that one. I'd want our engineer to answer it. What would you need to see?" Never guess.
A4: She asks | B4: Say it plainly | C4: Where it comes from
A5: What is Nutanix? | B5: It puts your servers, your storage and your networking into one system, so you manage it all from one place instead of three separate things. | C5: Your tick sheet
A6: What does hyperconverged mean? | B6: Servers, storage and networking handled in software on standard hardware, managed in one place. | C6: Your tick sheet
A7: What is AHV? | B7: The hypervisor that runs the virtual machines. Nutanix says it is included in the licence at no additional cost. | C7: Nutanix infographic (vendor claim): https://www.nutanix.com/library/infographics/safeguard-against-risks-arising-from-the-vmware-acquisition
A8: What is Prism? | B8: The management console. One hospital group said it manages production and disaster recovery centrally through it, including upgrades and troubleshooting. | C8: Nutanix press release, 2020 (vendor claim, one customer): https://www.nutanix.com/press-releases/2020/gruppo-policlinico-di-monza-healthcare-system-chooses-nutanix-to-improve-security-reliability-and-dr
A9: How would we move our VMs? | B9: A tool called Nutanix Move. It copies the data across ahead of time, can test the VMs in an isolated network first, and has rollback options that keep the original VM. It doesn't give a downtime figure, so never promise zero. | C9: Nutanix blog (vendor claim): https://www.nutanix.com/blog/supercharge-your-vm-migrations-to-nutanix-ahv
A10: Do we have to throw out our current storage? | B10: Nutanix says it can run alongside an existing SAN, or replace it. Which fits depends on your estate, so that's part of the comparison. | C10: Nutanix infographic (vendor claim): https://www.nutanix.com/library/infographics/safeguard-against-risks-arising-from-the-vmware-acquisition
A11: Can we use our existing VMware licences? | B11: Nutanix says existing vSphere licences can be applied to its platform. I'd want to check your exact licences in the comparison. | C11: Nutanix infographic (vendor claim): https://www.nutanix.com/library/infographics/safeguard-against-risks-arising-from-the-vmware-acquisition
A12: Why are customers looking at Nutanix? | B12: Broadcom bought VMware, not merged, causing price hikes and licensing changes that are pushing customers to look elsewhere, including Nutanix. | C12: Your tick sheet
A13: Are you big enough / stable? | B13: About $2.55B annual recurring revenue (ARR), up 16%, with 3,000+ new customers, and the CEO expects lots of VMware migration over the next five years. Only if she asks; don't push it. | C13: Your tick sheet

Sheet Objections
A1: Objections: agree, don't over-promise, ask what she needs
A2: Never run down VMware. You never defend Nutanix: you ask her what good looks like, then build that.
A4: She says | B4: She's worried | C4: Say this | D4: Why it works
A5: "Can you guarantee no downtime?" | B5: Patient systems going down. | C5: "That's the right thing to worry about. I can't promise zero downtime, and nobody honest can. What would you need to see in a plan to feel safe?" | D5: Admitting the limit earns trust. Her answer is the safety plan.
A6: "My team would need retraining." | B6: A stretched team can't cope. | C6: "That's a real cost, so we put it in the comparison. What would help most: training time, or someone supporting you during the move?" | D6: You treat the cost as real and give her a choice.
A7: "Is it cheaper? The reseller said so." | B7: She's wasting her time. | C7: "I can't promise that, because I haven't seen your setup yet. What would you need to see to know if it's worth it?" Then: "You said [her ceiling] is what you can absorb. Is that still true?" | D7: You refuse to promise what you can't prove. It leads to the costed comparison.
A8: "What about compliance? This is patient data." | B8: Breaking rules. | C8: "That's a big one, and I'd want an expert to answer it properly, not me. Who looks after that on your side?" | D8: Honest, and you get the compliance lead's name for the buying box.
A9: "Can you prove it will work for us?" | B9: She doesn't trust a claim. | C9: "I can't prove that today. That's exactly what the comparison is for." | D9: Turns 'no' into the reason for the next meeting.

Sheet Lookup
A1: Lookup: her pain -> what we DO, plus the targeted questions
A2: Pick a pain type on the Call tab and the 'We do' line (Pitch tab) and the targeted questions (Call tab) appear. Column C always starts with a verb because the pitch reads 'We [column C].' It describes what WE do, never a promise about the product.
A3: Supporting facts are vendor claims from the pages in column F. Say them only if she asks, and name the source. You can add your own rows under the last one (the dropdowns read down to row 25).
A5: Pain type (dropdown key) | B5: What she might say | C5: We do (X): starts with a verb | D5: Supporting fact (only if she asks) | E5: Source status | F5: Source URL | G5: Caution | H5: Targeted root-cause question (step 4) | I5: Targeted impact question (step 5)
A6: No tested fallback | B6: "I can't say to VMware we've tested another option." | C6: build a tested way back before anything moves | D6: Nutanix Move can create test VMs on the target site in an isolated network, and built-in rollback options keep the source VM (disconnected and annotated). Vendor blog. | E6: Nutanix page | F6: https://www.nutanix.com/blog/supercharge-your-vm-migrations-to-nutanix-ahv | G6: Say what we BUILD together. Don't say Nutanix removes all risk. | H6: To what extent is having no tested alternative weakening your position with VMware? | I6: Is the board asking what your plan B is, and is that a concern right now?
A7: Migration risk / downtime | B7: "If it goes wrong mid-migration, patient systems go down." | C7: start with non-critical workloads, test first, and agree the cutover windows with your clinical teams | D7: Move pre-seeds data and does delta syncs so cutovers cause minimal disruption. The page gives no downtime figures. | E7: Nutanix page | F7: https://www.nutanix.com/blog/supercharge-your-vm-migrations-to-nutanix-ahv | G7: NEVER promise zero downtime. 'I can't promise zero downtime, what would you need in a plan?' | H7: To what extent is the risk of an outage during a move what is holding you back? | I7: If a migration went wrong, who would feel it first, and how?
A8: CFO needs numbers | B8: "The CFO has to defend a number to the board." | C8: cost it side by side with your VMware quote, using your real estate numbers | D8: Nutanix says the AHV hypervisor is included in its licences at no additional cost, and existing vSphere licences can be applied to the platform. Vendor claim. | E8: Nutanix page | F8: https://www.nutanix.com/library/infographics/safeguard-against-risks-arising-from-the-vmware-acquisition | G8: Do NOT say it will be cheaper. Say: 'I haven't seen your estate, that's what the comparison is for.' | H8: To what extent is a lack of real numbers on the alternatives a problem when you talk to finance? | I8: How is finance reacting to the jump, and is that a concern right now?
A9: Renewal cost shock | B9: "The quote is more than double what we pay now." | C9: put a costed comparison next to your renewal quote before the board meets | D9: Same licensing points as above (AHV included, vSphere licence mobility). Vendor claim. | E9: Nutanix page | F9: https://www.nutanix.com/library/infographics/safeguard-against-risks-arising-from-the-vmware-acquisition | G9: Never promise a saving. Compare, don't claim. | H9: To what extent is the licensing change driving the increase, compared with what you actually use? | I9: What gets cut or delayed if the quote stands, and is that a concern right now?
A10: Small team capacity | B10: "My team is stretched and only knows VMware." | C10: put our engineer and the reseller alongside your team, with training time agreed up front | D10: Nutanix lists migration tools, training, professional services and a migration blueprint. Vendor claim. | E10: Nutanix page | F10: https://www.nutanix.com/library/infographics/safeguard-against-risks-arising-from-the-vmware-acquisition | G10: Ask: 'Training time, or support during the move?' Don't promise a learning-curve length. | H10: To what extent is your team's time, or only knowing one platform, an issue? | I10: What does it cost the hospital when the team is tied up with this?
A11: Storage end of support | B11: "The arrays go out of support at the end of next year." | C11: keep the storage replacement in the same plan, so it's sorted before the arrays go out of support | D11: Nutanix positions hyperconverged infrastructure as a SAN replacement, and says it can also run alongside an existing SAN for current workloads. Vendor claim. | E11: Nutanix page | F11: https://www.nutanix.com/library/infographics/safeguard-against-risks-arising-from-the-vmware-acquisition | G11: The date comes from HER. Don't say it fixes the storage on its own, say it goes in the plan. | H11: To what extent is the end-of-support date on the arrays forcing the timing? | I11: What happens to patient-facing systems if the arrays fail before they're replaced?
A12: Servers and storage as two worlds | B12: "Vendors blame each other and my people are stuck in the middle." | C12: bring servers, storage and networking into one system you manage from one place | D12: A healthcare customer (Gruppo Policlinico di Monza, 2020) said production and DR are managed centrally through Prism. Vendor press release, single customer. | E12: Nutanix page | F12: https://www.nutanix.com/press-releases/2020/gruppo-policlinico-di-monza-healthcare-system-chooses-nutanix-to-improve-security-reliability-and-dr | G12: One customer, 2020, vendor-published. Use as 'one hospital group did X', never as a general promise. | H12: To what extent does managing servers and storage separately slow you down when something breaks? | I12: How much team time goes on vendors pointing at each other, and is that a concern right now?
A13: Clinical uptime / patient safety | B13: "Patient systems are the one thing I can't be wrong about." | C13: agree migration windows with your clinical teams and name an engineer who is on call during the cutover | D13: The same customer reported RPO and RTO down 80% on average and storage snapshots at minute intervals. Vendor claim, one customer. | E13: Nutanix page | F13: https://www.nutanix.com/press-releases/2020/gruppo-policlinico-di-monza-healthcare-system-chooses-nutanix-to-improve-security-reliability-and-dr | G13: Don't quote the 80% as a promise. Only if she asks for evidence, and name the source. | H13: To what extent does clinical uptime limit how and when you can change anything? | I13: Who in the clinical teams feels it first when systems are unstable?
A14: Board wants less single-vendor risk | B14: "The board wants us less dependent on one vendor." | C14: give you a tested alternative on the table before the board meets, so you're not tied to one quote | D14: Nutanix Move migrates VMware workloads to AHV on-premises, to edge, and to public cloud. Vendor blog. | E14: Nutanix page | F14: https://www.nutanix.com/blog/supercharge-your-vm-migrations-to-nutanix-ahv | G14: Never run down VMware. She chose it and it has worked for ten years. | H14: To what extent is the board's push on single-vendor risk shaping the decision? | I14: How would it look at the board if you signed the renewal with no alternative?
A15: Compliance / patient data | B15: "Anything touching patient systems needs the compliance lead's sign-off." | C15: bring in a compliance expert to answer in writing, and agree who covers it on your side | D15: The Monza release names GDPR requirements and security as goals but states no specific security outcome. | E15: Nutanix page | F15: https://www.nutanix.com/press-releases/2020/gruppo-policlinico-di-monza-healthcare-system-chooses-nutanix-to-improve-security-reliability-and-dr | G15: Don't claim compliance. 'I'd want an expert to answer that. Who covers it on your side?' | H15: To what extent does compliance sign-off slow or shape any change to patient systems? | I15: Who covers compliance on your side, and what would they need to see?
A16: Paying for a suite we don't use | B16: "We're paying for a lot we don't use." | C16: map what you actually use against what you're being quoted for | D16: No public Nutanix source. This is a discovery step you run with her. | E16: Role-play / your own plan, not a Nutanix claim | G16: Don't claim savings. It's a question, not a promise. | H16: To what extent are you paying for parts of the licence you don't use? | I16: What would that money otherwise go to?
